oraqle/__init__.py
oraqle/config.py
oraqle/add_chains/__init__.py
oraqle/add_chains/addition_chains.py
oraqle/add_chains/addition_chains_front.py
oraqle/add_chains/addition_chains_heuristic.py
oraqle/add_chains/addition_chains_mod.py
oraqle/add_chains/memoization.py
oraqle/add_chains/solving.py
oraqle/circuits/__init__.py
oraqle/circuits/aes.py
oraqle/circuits/cardio.py
oraqle/circuits/median.py
oraqle/circuits/mimc.py
oraqle/circuits/sorting.py
oraqle/circuits/veto_voting.py
oraqle/compiler/__init__.py
oraqle/compiler/circuit.py
oraqle/compiler/func2poly.py
oraqle/compiler/graphviz.py
oraqle/compiler/instructions.py
oraqle/compiler/poly2circuit.py
oraqle/compiler/arithmetic/__init__.py
oraqle/compiler/arithmetic/exponentiation.py
oraqle/compiler/arithmetic/subtraction.py
oraqle/compiler/boolean/__init__.py
oraqle/compiler/boolean/bool_and.py
oraqle/compiler/boolean/bool_neg.py
oraqle/compiler/boolean/bool_or.py
oraqle/compiler/comparison/__init__.py
oraqle/compiler/comparison/comparison.py
oraqle/compiler/comparison/equality.py
oraqle/compiler/comparison/in_upper_half.py
oraqle/compiler/control_flow/__init__.py
oraqle/compiler/control_flow/conditional.py
oraqle/compiler/nodes/__init__.py
oraqle/compiler/nodes/abstract.py
oraqle/compiler/nodes/arbitrary_arithmetic.py
oraqle/compiler/nodes/binary_arithmetic.py
oraqle/compiler/nodes/fixed.py
oraqle/compiler/nodes/flexible.py
oraqle/compiler/nodes/leafs.py
oraqle/compiler/nodes/non_commutative.py
oraqle/compiler/nodes/unary_arithmetic.py
oraqle/compiler/nodes/univariate.py
oraqle/compiler/polynomials/__init__.py
oraqle/compiler/polynomials/univariate.py
oraqle/examples/depth_aware_comparison.py
oraqle/examples/depth_aware_equality.py
oraqle/examples/long_and.py
oraqle/examples/small_comparison.py
oraqle/examples/small_polynomial.py
oraqle/examples/visualize_circuits.py
oraqle/examples/wahc2024_presentation/1_high-level.py
oraqle/examples/wahc2024_presentation/2_arith_step1.py
oraqle-0.1.5.dist-info/LICENSE.txt
oraqle-0.1.5.dist-info/METADATA
oraqle-0.1.5.dist-info/WHEEL
oraqle-0.1.5.dist-info/top_level.txt
oraqle-0.1.5.dist-info/RECORD
