Metadata-Version: 2.1
Name: oraqle
Version: 0.1.5
Summary: Secure computation compiler for homomorphic encryption and arithmetic circuits in general
Author-email: Jelle Vos <J.V.Vos@tudelft.nl>
Maintainer-email: Jelle Vos <J.V.Vos@tudelft.nl>
Requires-Python: >=3.8
License-File: LICENSE.txt
